{
  "projects": [
    {
      "id": "6660",
      "name": "TesteProjeto",
      "budget": "100000",
      "category": {
        "id": "2",
        "name": "Desenvolvimento"
      },
      "cost": 10,
      "services": [
        {
          "name": "TesteTarefa",
          "cost": "10",
          "description": "teste",
          "id": "cc78e2a9-a6e4-4b2f-b437-87a3f84f53ff",
          "projectID": "6660",
          "equipe": [
            {
              "nameColab": "Pedro",
              "funcao": {
                "id": "2",
                "name": "Testes"
              }
            }
          ]
        }
      ],
      "user_email": "joaovitorteixeiradesouza2@gmail.com",
      "date": "2024-04-10"
    },
    {
      "id": "1c7f",
      "name": "TESTE",
      "budget": "101",
      "category": {
        "id": "1",
        "name": "Infraestrutura"
      },
      "cost": 1,
      "services": [
        {
          "name": "testeTarefa",
          "cost": "1",
          "description": "100",
          "id": "98751b32-718c-4a96-8112-eba45c1131ae",
          "projectID": "1c7f",
          "equipe": [
            {
              "nameColab": "Pedro",
              "funcao": {
                "id": "2",
                "name": "Testes"
              }
            }
          ]
        }
      ],
      "user_email": "joaovitorteixeiradesouza2@gmail.com",
      "date": "2024-04-11"
    },
    {
      "id": "9146",
      "name": "TESTE123",
      "budget": "101",
      "category": {
        "id": "2",
        "name": "Desenvolvimento"
      },
      "date": "2024-04-24",
      "cost": 32,
      "services": [
        {
          "name": "TesteTarefa",
          "cost": "32",
          "description": "teste",
          "date": "2024-04-19",
          "id": "f4ef4a06-ad2c-4eca-b021-d70753bde2c7",
          "projectID": "9146",
          "equipe": [
            {
              "nameColab": "Rocha",
              "funcao": {
                "id": "1",
                "name": "Desenvolvimento"
              }
            }
          ]
        }
      ],
      "user_email": "joaovitorteixeiradesouza2@gmail.com"
    }
  ],
  "categories": [
    {
      "id": "1",
      "name": "Infraestrutura"
    },
    {
      "id": "2",
      "name": "Desenvolvimento"
    },
    {
      "id": "3",
      "name": "Design"
    },
    {
      "id": "4",
      "name": "Planejamento"
    }
  ],
  "funcoes": [
    {
      "id": "1",
      "name": "Desenvolvimento"
    },
    {
      "id": "2",
      "name": "Testes"
    },
    {
      "id": "3",
      "name": "Responsável"
    }
  ],
  "users": [
    {
      "id": "bd3e",
      "nome": "teste",
      "email": "joaovitorteixeiradesouza1@gmail.com",
      "password": "$2a$10$0Vm5Iw.7.QPlcPZI2V/iOe4VEz00eSjVEBaUZJ7aK5yKJBYlfUG26"
    },
    {
      "id": "591a",
      "nome": "Teste2",
      "email": "joaovitorteixeiradesouza2@gmail.com",
      "password": "$2a$10$H9OZq2LXlOHjPmE4QerPQObw7lwzlQxI0aDXozh8Jo7w23p6pLyde"
    }
  ]
}